spoon_ec5fd18c/__init__.py
spoon_ec5fd18c/__main__.py
spoon_ec5fd18c/_cli.py
spoon_ec5fd18c/_lib.py
spoon_ec5fd18c/_version.py
spoon_ec5fd18c-0.1.18.dist-info/licenses/LICENSE
spoon_ec5fd18c-0.1.18.dist-info/WHEEL
spoon_ec5fd18c-0.1.18.dist-info/entry_points.txt
spoon_ec5fd18c-0.1.18.dist-info/METADATA
spoon_ec5fd18c-0.1.18.dist-info/RECORD
