Metadata-Version: 2.4
Name: spoon-ec5fd18c
Version: 0.1.18
Summary: An experimental Python project that explores modern Python development best practices and GitHub workflows
Author: guantao.gao
Author-email: guantao.gao <guantao.gao@clickzetta.com>
License-Expression: Apache-2.0
License-File: LICENSE
Classifier: Development Status :: 3 - Alpha
Classifier: Intended Audience :: Developers
Classifier: Topic :: Software Development :: Libraries :: Python Modules
Classifier: Programming Language :: Python :: 3
Classifier: Programming Language :: Python :: 3.10
Classifier: Programming Language :: Python :: 3.11
Classifier: Programming Language :: Python :: 3.12
Classifier: Programming Language :: Python :: 3.13
Classifier: Operating System :: OS Independent
Classifier: License :: OSI Approved :: Apache Software License
Requires-Dist: typer-slim>=0.17.3 ; extra == 'cli'
Requires-Python: >=3.10
Project-URL: Homepage, https://github.com/czudf/spoon
Project-URL: Issues, https://github.com/czudf/spoon/issues
Project-URL: Repository, https://github.com/czudf/spoon
Provides-Extra: cli
